Metadata-Version: 2.1
Name: odoo-addon-l10n_it_delivery_note_base
Version: 16.0.1.0.2.6
Requires-Python: >=3.10
Requires-Dist: odoo>=16.0a,<16.1dev
Summary: Crea e gestisce tabelle principali per gestire i DDT
Home-page: https://github.com/OCA/l10n-italy
License: AGPL-3
Author: Marco Calcagni, Gianmarco Conte, Link IT Europe Srl, Odoo Community Association (OCA)
Author-email: support@odoo-community.org
Classifier: Programming Language :: Python
Classifier: Framework :: Odoo
Classifier: Framework :: Odoo :: 16.0
Classifier: License :: OSI Approved :: GNU Affero General Public License v3
